[
    {
        "station_number": 24,
        "date": "2024-04-11 17:10:03",
        "temperature": 19.350000381469727,
        "relative_humidity": 49.0,
        "dew_point": 8.364592552185059,
        "apparent_temperature": 18.104949951171875,
        "precipitation_probability": 0.0,
        "rain": 0.0,
        "surface_pressure": 996.1123657226562
    },
    {
        "station_number": 10,
        "date": "2024-04-11 17:10:03",
        "temperature": 19.5,
        "relative_humidity": 49.0,
        "dew_point": 8.502291679382324,
        "apparent_temperature": 18.19942283630371,
        "precipitation_probability": 0.0,
        "rain": 0.0,
        "surface_pressure": 997.6515502929688
    },
    {
        "station_number": 9,
        "date": "2024-04-11 17:10:03",
        "temperature": 19.5,
        "relative_humidity": 49.0,
        "dew_point": 8.502291679382324,
        "apparent_temperature": 18.19942283630371,
        "precipitation_probability": 0.0,
        "rain": 0.0,
        "surface_pressure": 997.0728759765625
    },
    {
        "station_number": 13,
        "date": "2024-04-11 17:10:03",
        "temperature": 19.200000762939453,
        "relative_humidity": 50.0,
        "dew_point": 8.525004386901855,
        "apparent_temperature": 17.894878387451172,
        "precipitation_probability": 0.0,
        "rain": 0.0,
        "surface_pressure": 997.735595703125
    },
    {
        "station_number": 20,
        "date": "2024-04-11 17:10:03",
        "temperature": 19.299999237060547,
        "relative_humidity": 50.0,
        "dew_point": 8.617025375366211,
        "apparent_temperature": 18.01896095275879,
        "precipitation_probability": 0.0,
        "rain": 0.0,
        "surface_pressure": 999.0215454101562
    },
    {
        "station_number": 4,
        "date": "2024-04-11 17:10:03",
        "temperature": 19.5,
        "relative_humidity": 49.0,
        "dew_point": 8.502291679382324,
        "apparent_temperature": 18.19942283630371,
        "precipitation_probability": 0.0,
        "rain": 0.0,
        "surface_pressure": 997.420166015625
    },
    {
        "station_number": 1,
        "date": "2024-04-11 17:10:03",
        "temperature": 19.350000381469727,
        "relative_humidity": 51.0,
        "dew_point": 8.95626163482666,
        "apparent_temperature": 18.234249114990234,
        "precipitation_probability": 0.0,
        "rain": 0.0,
        "surface_pressure": 996.59375
    },
    {
        "station_number": 16,
        "date": "2024-04-11 17:10:03",
        "temperature": 19.5,
        "relative_humidity": 49.0,
        "dew_point": 8.502291679382324,
        "apparent_temperature": 18.19942283630371,
        "precipitation_probability": 0.0,
        "rain": 0.0,
        "surface_pressure": 997.420166015625
    },
    {
        "station_number": 3,
        "date": "2024-04-11 17:10:03",
        "temperature": 19.450000762939453,
        "relative_humidity": 49.0,
        "dew_point": 8.45639419555664,
        "apparent_temperature": 18.13747787475586,
        "precipitation_probability": 0.0,
        "rain": 0.0,
        "surface_pressure": 996.7203979492188
    },
    {
        "station_number": 21,
        "date": "2024-04-11 17:10:03",
        "temperature": 19.450000762939453,
        "relative_humidity": 49.0,
        "dew_point": 8.45639419555664,
        "apparent_temperature": 18.13747787475586,
        "precipitation_probability": 0.0,
        "rain": 0.0,
        "surface_pressure": 996.6047973632812
    },
    {
        "station_number": 6,
        "date": "2024-04-11 17:10:03",
        "temperature": 19.5,
        "relative_humidity": 49.0,
        "dew_point": 8.502291679382324,
        "apparent_temperature": 18.19942283630371,
        "precipitation_probability": 0.0,
        "rain": 0.0,
        "surface_pressure": 997.420166015625
    },
    {
        "station_number": 22,
        "date": "2024-04-11 17:10:03",
        "temperature": 19.350000381469727,
        "relative_humidity": 49.0,
        "dew_point": 8.364592552185059,
        "apparent_temperature": 18.104949951171875,
        "precipitation_probability": 0.0,
        "rain": 0.0,
        "surface_pressure": 996.574951171875
    },
    {
        "station_number": 14,
        "date": "2024-04-11 17:10:03",
        "temperature": 19.450000762939453,
        "relative_humidity": 49.0,
        "dew_point": 8.45639419555664,
        "apparent_temperature": 18.13747787475586,
        "precipitation_probability": 0.0,
        "rain": 0.0,
        "surface_pressure": 996.6047973632812
    },
    {
        "station_number": 19,
        "date": "2024-04-11 17:10:03",
        "temperature": 19.149999618530273,
        "relative_humidity": 50.0,
        "dew_point": 8.47899055480957,
        "apparent_temperature": 17.832881927490234,
        "precipitation_probability": 0.0,
        "rain": 0.0,
        "surface_pressure": 996.9188842773438
    },
    {
        "station_number": 25,
        "date": "2024-04-11 17:10:03",
        "temperature": 19.350000381469727,
        "relative_humidity": 49.0,
        "dew_point": 8.364592552185059,
        "apparent_temperature": 18.104949951171875,
        "precipitation_probability": 0.0,
        "rain": 0.0,
        "surface_pressure": 996.6905517578125
    },
    {
        "station_number": 17,
        "date": "2024-04-11 17:10:03",
        "temperature": 19.350000381469727,
        "relative_humidity": 51.0,
        "dew_point": 8.95626163482666,
        "apparent_temperature": 18.234249114990234,
        "precipitation_probability": 0.0,
        "rain": 0.0,
        "surface_pressure": 996.2470092773438
    },
    {
        "station_number": 28,
        "date": "2024-04-11 17:10:03",
        "temperature": 19.549999237060547,
        "relative_humidity": 49.0,
        "dew_point": 8.548188209533691,
        "apparent_temperature": 18.261402130126953,
        "precipitation_probability": 0.0,
        "rain": 0.0,
        "surface_pressure": 998.5835571289062
    },
    {
        "station_number": 8,
        "date": "2024-04-11 17:10:03",
        "temperature": 19.149999618530273,
        "relative_humidity": 50.0,
        "dew_point": 8.47899055480957,
        "apparent_temperature": 17.832881927490234,
        "precipitation_probability": 0.0,
        "rain": 0.0,
        "surface_pressure": 996.57177734375
    },
    {
        "station_number": 7,
        "date": "2024-04-11 17:10:03",
        "temperature": 19.149999618530273,
        "relative_humidity": 50.0,
        "dew_point": 8.47899055480957,
        "apparent_temperature": 17.832881927490234,
        "precipitation_probability": 0.0,
        "rain": 0.0,
        "surface_pressure": 997.034912109375
    },
    {
        "station_number": 2,
        "date": "2024-04-11 17:10:03",
        "temperature": 19.450000762939453,
        "relative_humidity": 49.0,
        "dew_point": 8.45639419555664,
        "apparent_temperature": 18.13747787475586,
        "precipitation_probability": 0.0,
        "rain": 0.0,
        "surface_pressure": 996.8362426757812
    },
    {
        "station_number": 5,
        "date": "2024-04-11 17:10:03",
        "temperature": 19.450000762939453,
        "relative_humidity": 49.0,
        "dew_point": 8.45639419555664,
        "apparent_temperature": 18.13747787475586,
        "precipitation_probability": 0.0,
        "rain": 0.0,
        "surface_pressure": 996.4891357421875
    },
    {
        "station_number": 12,
        "date": "2024-04-11 17:10:03",
        "temperature": 19.200000762939453,
        "relative_humidity": 50.0,
        "dew_point": 8.525004386901855,
        "apparent_temperature": 17.894878387451172,
        "precipitation_probability": 0.0,
        "rain": 0.0,
        "surface_pressure": 997.6195068359375
    },
    {
        "station_number": 29,
        "date": "2024-04-11 17:10:03",
        "temperature": 19.600000381469727,
        "relative_humidity": 49.0,
        "dew_point": 8.59408950805664,
        "apparent_temperature": 18.323415756225586,
        "precipitation_probability": 0.0,
        "rain": 0.0,
        "surface_pressure": 998.8204956054688
    },
    {
        "station_number": 15,
        "date": "2024-04-11 17:10:03",
        "temperature": 19.350000381469727,
        "relative_humidity": 49.0,
        "dew_point": 8.364592552185059,
        "apparent_temperature": 18.104949951171875,
        "precipitation_probability": 0.0,
        "rain": 0.0,
        "surface_pressure": 996.6905517578125
    },
    {
        "station_number": 26,
        "date": "2024-04-11 17:10:03",
        "temperature": 18.700000762939453,
        "relative_humidity": 56.0,
        "dew_point": 9.744184494018555,
        "apparent_temperature": 17.890777587890625,
        "precipitation_probability": 0.0,
        "rain": 0.0,
        "surface_pressure": 996.2709350585938
    },
    {
        "station_number": 23,
        "date": "2024-04-11 17:10:03",
        "temperature": 19.350000381469727,
        "relative_humidity": 49.0,
        "dew_point": 8.364592552185059,
        "apparent_temperature": 18.104949951171875,
        "precipitation_probability": 0.0,
        "rain": 0.0,
        "surface_pressure": 996.922119140625
    },
    {
        "station_number": 27,
        "date": "2024-04-11 17:10:03",
        "temperature": 19.350000381469727,
        "relative_humidity": 50.0,
        "dew_point": 8.663037300109863,
        "apparent_temperature": 18.0810546875,
        "precipitation_probability": 0.0,
        "rain": 0.0,
        "surface_pressure": 999.9552001953125
    },
    {
        "station_number": 18,
        "date": "2024-04-11 17:10:03",
        "temperature": 19.350000381469727,
        "relative_humidity": 51.0,
        "dew_point": 8.95626163482666,
        "apparent_temperature": 18.234249114990234,
        "precipitation_probability": 0.0,
        "rain": 0.0,
        "surface_pressure": 996.7093505859375
    },
    {
        "station_number": 11,
        "date": "2024-04-11 17:10:03",
        "temperature": 19.149999618530273,
        "relative_humidity": 50.0,
        "dew_point": 8.47899055480957,
        "apparent_temperature": 17.832881927490234,
        "precipitation_probability": 0.0,
        "rain": 0.0,
        "surface_pressure": 997.034912109375
    }
]